docs/source/conf.py
omusic/__init__.py
omusic/chord.py
omusic/guitar.py
omusic/midi.py
omusic/modes.py
omusic/py.typed
omusic/scale.py
omusic-0.0.1.dist-info/licenses/LICENSE.txt
omusic-0.0.1.dist-info/METADATA
omusic-0.0.1.dist-info/WHEEL
omusic-0.0.1.dist-info/top_level.txt
omusic-0.0.1.dist-info/RECORD
